test_github_ci-0.0.13.dist-info/METADATA
test_github_ci-0.0.13.dist-info/WHEEL
test_github_ci-0.0.13.dist-info/entry_points.txt
test_github_ci/__init__.py
test_github_ci/hello.py
test_github_ci-0.0.13.dist-info/RECORD
