Metadata-Version: 2.1
Name: test-github-ci
Version: 0.0.13
Summary: This project tests AutoPub with GitHub Actions CI.
Author-Email: BotPub <52496925+botpub@users.noreply.github.com>
Requires-Python: ~=3.10
